MANIFEST.in
README.txt
VERSION.txt
setup.py
mamaslemonpy/__init__.py
mamaslemonpy/__main__.py
mamaslemonpy/buildindex.py
mamaslemonpy/core.py
mamaslemonpy/mapcount.py
mamaslemonpy/match.py
mamaslemonpy/names.py
mamaslemonpy/qgramshapes.py
mamaslemonpy/seqs.py
mamaslemonpy/showprofile.py
mamaslemonpy/statistics.py
mamaslemonpy/suffix.py
mamaslemonpy/suffix2.py
mamaslemonpy/translate.py
mamaslemonpy/utils.py
mamaslemonpy.egg-info/PKG-INFO
mamaslemonpy.egg-info/SOURCES.txt
mamaslemonpy.egg-info/dependency_links.txt
mamaslemonpy.egg-info/requires.txt
mamaslemonpy.egg-info/top_level.txt