Metadata-Version: 1.1
Name: mamaslemonpy
Version: 0.98
Summary: index biological sequences and run maximial matches queries on them
Home-page: https://bitbucket.org/svenrahmann/mamaslemonpy/
Author: Sven Rahmann
Author-email: Sven.Rahmann@gmail.com
License: MIT
Platform: UNKNOWN
Classifier: Development Status :: 5 - Production/Stable
Classifier: Intended Audience :: Developers
Classifier: Intended Audience :: Science/Research
Classifier: Natural Language :: English
Classifier: License :: OSI Approved :: MIT License
Classifier: Operating System :: OS Independent
Classifier: Programming Language :: Python
Classifier: Programming Language :: Python :: 3
Classifier: Programming Language :: Python :: 3.2
Classifier: Programming Language :: Python :: 3.3
Classifier: Programming Language :: Python :: 3.4
Classifier: Topic :: Scientific/Engineering :: Bio-Informatics
